{
  "generated_at": "2026-02-06T16:41:52.693651Z",
  "lookbacks": {
    "30": {
      "lookback_days": 30,
      "corr": 0.89702420403109,
      "stats": {
        "mean": {
          "btc": -0.0003578333816756002,
          "eth": -0.0005765725835320437
        },
        "std": {
          "btc": 0.005805464211935726,
          "eth": 0.008224393406186744
        },
        "min": {
          "btc": -0.031142278584685545,
          "eth": -0.04170398539552955
        },
        "max": {
          "btc": 0.0349913262434709,
          "eth": 0.04377388676562077
        }
      },
      "hedge_table": [
        {
          "target": "BTC",
          "hedge": "ETH",
          "hedge_ratio_units": 0.6331946511490087,
          "target_w": 0.6122968865324568,
          "hedge_w": -0.38770311346754316
        },
        {
          "target": "ETH",
          "hedge": "BTC",
          "hedge_ratio_units": 1.2707820907164498,
          "target_w": 0.4403769098269099,
          "hedge_w": -0.55962309017309
        }
      ],
      "examples": [
        {
          "target": "BTC",
          "hedge": "ETH",
          "target_dollars": 61.22968865324568,
          "hedge_dollars": -38.77031134675432,
          "hedge_units_per_target_unit": -0.6331946511490087
        },
        {
          "target": "ETH",
          "hedge": "BTC",
          "target_dollars": 44.03769098269099,
          "hedge_dollars": -55.962309017308996,
          "hedge_units_per_target_unit": -1.2707820907164498
        }
      ]
    },
    "60": {
      "lookback_days": 60,
      "corr": 0.8980774072737502,
      "stats": {
        "mean": {
          "btc": -0.0001673942172810654,
          "eth": -0.000273228753365949
        },
        "std": {
          "btc": 0.005069640354422603,
          "eth": 0.007149507041814726
        },
        "min": {
          "btc": -0.031142278584685545,
          "eth": -0.04988725258205495
        },
        "max": {
          "btc": 0.0349913262434709,
          "eth": 0.04377388676562077
        }
      },
      "hedge_table": [
        {
          "target": "BTC",
          "hedge": "ETH",
          "hedge_ratio_units": 0.6368172572852768,
          "target_w": 0.6109417502467793,
          "hedge_w": -0.3890582497532206
        },
        {
          "target": "ETH",
          "hedge": "BTC",
          "hedge_ratio_units": 1.2665219420934004,
          "target_w": 0.4412046410970908,
          "hedge_w": -0.5587953589029091
        }
      ],
      "examples": [
        {
          "target": "BTC",
          "hedge": "ETH",
          "target_dollars": 61.09417502467793,
          "hedge_dollars": -38.90582497532206,
          "hedge_units_per_target_unit": -0.6368172572852768
        },
        {
          "target": "ETH",
          "hedge": "BTC",
          "target_dollars": 44.120464109709076,
          "hedge_dollars": -55.87953589029091,
          "hedge_units_per_target_unit": -1.2665219420934004
        }
      ]
    },
    "120": {
      "lookback_days": 120,
      "corr": 0.8808603444418573,
      "stats": {
        "mean": {
          "btc": -0.00017873044202714386,
          "eth": -0.0002346008611942472
        },
        "std": {
          "btc": 0.0051472674550082104,
          "eth": 0.007606911940449292
        },
        "min": {
          "btc": -0.03714671634653788,
          "eth": -0.05178573218862892
        },
        "max": {
          "btc": 0.0349913262434709,
          "eth": 0.04377388676562077
        }
      },
      "hedge_table": [
        {
          "target": "BTC",
          "hedge": "ETH",
          "hedge_ratio_units": 0.5960399987337173,
          "target_w": 0.6265507135118107,
          "hedge_w": -0.3734492864881893
        },
        {
          "target": "ETH",
          "hedge": "BTC",
          "hedge_ratio_units": 1.301783350209136,
          "target_w": 0.4344457526418122,
          "hedge_w": -0.5655542473581879
        }
      ],
      "examples": [
        {
          "target": "BTC",
          "hedge": "ETH",
          "target_dollars": 62.65507135118107,
          "hedge_dollars": -37.34492864881893,
          "hedge_units_per_target_unit": -0.5960399987337173
        },
        {
          "target": "ETH",
          "hedge": "BTC",
          "target_dollars": 43.44457526418122,
          "hedge_dollars": -56.5554247358188,
          "hedge_units_per_target_unit": -1.301783350209136
        }
      ]
    },
    "150": {
      "lookback_days": 150,
      "corr": 0.872805099591659,
      "stats": {
        "mean": {
          "btc": -0.00011808703288668178,
          "eth": -0.00018170852946711058
        },
        "std": {
          "btc": 0.004797663220946355,
          "eth": 0.007185146073460918
        },
        "min": {
          "btc": -0.03714671634653788,
          "eth": -0.05178573218862892
        },
        "max": {
          "btc": 0.0349913262434709,
          "eth": 0.04377388676562077
        }
      },
      "hedge_table": [
        {
          "target": "BTC",
          "hedge": "ETH",
          "hedge_ratio_units": 0.5827891155660719,
          "target_w": 0.6317961061049867,
          "hedge_w": -0.36820389389501335
        },
        {
          "target": "ETH",
          "hedge": "BTC",
          "hedge_ratio_units": 1.307143049734669,
          "target_w": 0.43343649632605324,
          "hedge_w": -0.5665635036739469
        }
      ],
      "examples": [
        {
          "target": "BTC",
          "hedge": "ETH",
          "target_dollars": 63.17961061049867,
          "hedge_dollars": -36.82038938950134,
          "hedge_units_per_target_unit": -0.5827891155660719
        },
        {
          "target": "ETH",
          "hedge": "BTC",
          "target_dollars": 43.34364963260533,
          "hedge_dollars": -56.656350367394694,
          "hedge_units_per_target_unit": -1.307143049734669
        }
      ]
    },
    "180": {
      "lookback_days": 180,
      "corr": 0.8543632016364584,
      "stats": {
        "mean": {
          "btc": -0.00011238392232411327,
          "eth": -0.00014351198386334575
        },
        "std": {
          "btc": 0.0046347241748411075,
          "eth": 0.00723196658443964
        },
        "min": {
          "btc": -0.03714671634653788,
          "eth": -0.05178573218862892
        },
        "max": {
          "btc": 0.0349913262434709,
          "eth": 0.0757825447476439
        }
      },
      "hedge_table": [
        {
          "target": "BTC",
          "hedge": "ETH",
          "hedge_ratio_units": 0.5475326439199741,
          "target_w": 0.6461899229905433,
          "hedge_w": -0.35381007700945666
        },
        {
          "target": "ETH",
          "hedge": "BTC",
          "hedge_ratio_units": 1.3331378291614429,
          "target_w": 0.4286073405099311,
          "hedge_w": -0.5713926594900689
        }
      ],
      "examples": [
        {
          "target": "BTC",
          "hedge": "ETH",
          "target_dollars": 64.61899229905434,
          "hedge_dollars": -35.381007700945666,
          "hedge_units_per_target_unit": -0.5475326439199741
        },
        {
          "target": "ETH",
          "hedge": "BTC",
          "target_dollars": 42.86073405099311,
          "hedge_dollars": -57.13926594900689,
          "hedge_units_per_target_unit": -1.3331378291614429
        }
      ]
    }
  },
  "example_notional": 100.0,
  "provider": "cryptocompare"
}